netcenlib/__init__.py
netcenlib/centrality.py
netcenlib/commons.py
netcenlib/constants.py
netcenlib/setup.py
netcenlib/taxonomies.py
netcenlib/version.py
netcenlib/algorithms/__init__.py
netcenlib/algorithms/algebraic_centrality.py
netcenlib/algorithms/average_distance_centrality.py
netcenlib/algorithms/barycenter_centrality.py
netcenlib/algorithms/bottle_neck_centrality.py
netcenlib/algorithms/centroid_centrality.py
netcenlib/algorithms/cluster_rank_centrality.py
netcenlib/algorithms/coreness_centrality.py
netcenlib/algorithms/decay_centrality.py
netcenlib/algorithms/diffusion_degree_centrality.py
netcenlib/algorithms/eccentricity_centrality.py
netcenlib/algorithms/entropy_centrality.py
netcenlib/algorithms/geodestic_k_path_centrality.py
netcenlib/algorithms/heatmap_centrality.py
netcenlib/algorithms/hubbell_centrality.py
netcenlib/algorithms/leverage_centrality.py
netcenlib/algorithms/lin_centrality.py
netcenlib/algorithms/mnc_centrality.py
netcenlib/algorithms/pdi_centrality.py
netcenlib/algorithms/radiality_centrality.py
netcenlib/algorithms/rumor_centrality.py
netcenlib/algorithms/semi_local_centrality.py
netcenlib/algorithms/topological_centrality.py
netcenlib/common/__init__.py
netcenlib/common/exceptions.py
netcenlib/common/nx_cached.py
netcenlib/common/nx_utils.py
netcenlib-0.2.2.dist-info/LICENSE
netcenlib-0.2.2.dist-info/METADATA
netcenlib-0.2.2.dist-info/WHEEL
netcenlib-0.2.2.dist-info/top_level.txt
netcenlib-0.2.2.dist-info/RECORD
